odoo/addons/l10n_ro_city/README.rst
odoo/addons/l10n_ro_city/__init__.py
odoo/addons/l10n_ro_city/__manifest__.py
odoo/addons/l10n_ro_city/data/res.city.csv
odoo/addons/l10n_ro_city/i18n/l10n_ro_city.pot
odoo/addons/l10n_ro_city/i18n/ro.po
odoo/addons/l10n_ro_city/models/__init__.py
odoo/addons/l10n_ro_city/models/res_city.py
odoo/addons/l10n_ro_city/models/res_partner.py
odoo/addons/l10n_ro_city/readme/CONTRIBUTORS.rst
odoo/addons/l10n_ro_city/readme/DESCRIPTION.rst
odoo/addons/l10n_ro_city/static/description/icon.png
odoo/addons/l10n_ro_city/static/description/icon.svg
odoo/addons/l10n_ro_city/static/description/index.html
odoo/addons/l10n_ro_city/tests/__init__.py
odoo/addons/l10n_ro_city/tests/test_ro_city.py
odoo/addons/l10n_ro_city/views/res_city_view.xml
odoo13_addon_l10n_ro_city-13.0.1.0.1.dist-info/METADATA
odoo13_addon_l10n_ro_city-13.0.1.0.1.dist-info/WHEEL
odoo13_addon_l10n_ro_city-13.0.1.0.1.dist-info/top_level.txt
odoo13_addon_l10n_ro_city-13.0.1.0.1.dist-info/RECORD
